bothlent_asr_eval/__init__.py
bothlent_asr_eval/__main__.py
bothlent_asr_eval/asr_evaluation.py
bothlent_asr_eval/package_data.dat
bothlent_asr_eval/simple.py
bothlent_asr_eval-1.1.0.data/data/bothlent_asr_eval_data/data_file
bothlent_asr_eval-1.1.0.dist-info/LICENSE.txt
bothlent_asr_eval-1.1.0.dist-info/METADATA
bothlent_asr_eval-1.1.0.dist-info/WHEEL
bothlent_asr_eval-1.1.0.dist-info/entry_points.txt
bothlent_asr_eval-1.1.0.dist-info/top_level.txt
bothlent_asr_eval-1.1.0.dist-info/RECORD
